{
    "published": "2022-01-02",
    "title": "因應極端氣候  黃偉哲市長積極爭取中央補助投入山坡地防災整治工作",
    "department": "新聞及國際關係處新聞傳播科",
    "url": "https:\/\/www.tainan.gov.tw\/News_Content.aspx?n=13370&s=7864163",
    "content": "發稿單位：水利局\n發稿時間：111年1月2日13:30\n\n臺南市轄內山坡地範圍橫跨14行政區，面積約8.2萬公頃，占臺南市總面積約38%，臺南市長黃偉哲認為，山區範圍遼闊，治山防災工作必須與中央攜手合作，因此市府積極與中央合作辦理山坡地野溪及坡地治理工程，也針對山區建置水位站12站、雨量站7站、影像監視站11站、淹水感測站29站以達到預警機制與智慧防災的效果。\n\n水利局說明，為了提升整體山坡地防災能量降低坡地災害發生機率，自黃偉哲市長上任以來，中央及市府合計投入經費約42.5億元，野溪治理長度約85公里，其中市府於110年度針對於山坡地範圍也投入3.1億元，野溪治理長度達6.2公里，另行政院農業委員會水土保持局臺南分局於110年亦投入約4億8,000萬元。\n\n水利局表示，臺灣降雨季節分配不均，極端氣候更造成降雨強度提升，因此土壤易受侵蝕嚴重，因此針對野溪整體治理工作，需以集水區之概念，分區段進行，惟鑒於山坡地範圍廣闊且需辦理整治件數眾多，後續除了依據案件輕重緩急逐一辦理外，也將積極爭取中央經費補助，以減低上游坡地災害發生機率，保障人民生命財產安全。\n\n水利局最後說明，111年度目前已爭取到行政院農業委員會水土保持局前瞻基礎建設計畫補助辦理7件山區水土保持工程，經費共計3,480萬元，為加速辦理山區野溪、土石流及崩塌治理，已於今年底先行啟動測設作業，111年初即可上網辦理發包作業，預計於汛期前即可完成急迫段整治，確保山區居民免受土砂災害，後續亦將持續向中央爭取經費補助，積極辦理山區建設。",
    "tags": "#水利 #水土保持"
}