{
    "published": "2021-11-12",
    "title": "臺南市東區仁和公共托育家園缺額招生 歡迎市民踴躍報名",
    "department": "新聞及國際關係處新聞傳播科",
    "url": "https:\/\/www.tainan.gov.tw\/News_Content.aspx?n=13370&s=7840797",
    "content": "發稿單位：社會局\n發稿時間：110年11月12日16:25\n\n本市東區仁和公共托育家園即日起開放招生報名，收托條件為110年11月26日(抽籤日)已滿2足月至未滿2足歲嬰幼兒，且父母雙方設籍於本市滿6個月以上。每名受托幼童每月托育費用1萬元，並依家庭經濟狀況及家中兒童數每月補助4,000元至1萬元，大大減輕家長育兒負擔。\n\n陳榮枝局長表示，為打造友善托育環境，積極增設公共托嬰設施，減輕家中托育寶貝的經濟負擔。社會局預計在111年再增設4處社區公共托育家園及1處公共托嬰中心，增加臺南市托育能量，朝社區化、在地化收托，創造一個友善養育跟教育的環境。每一處社區公共托育家園皆委託專業經驗豐富的托育團隊，提供健康快樂的優質照顧空間，讓孩子快樂成長。\n\n黃偉哲市長表示臺南市政府創全國之先，於109年針對公設民營托育家園全面建置「公共托育家園影像監管雲端伺服器系統」，將公共托育家園每日托育動態即時回傳相關影像至社會局，局內隨時可觀看幼兒受照顧情形，亦確保錄影資料保存30天及存檔，讓本市家園收托照顧兒童管理情形更加完善，讓家長能安心送托。\n\n本次報名採郵寄或電子郵件方式收件，報名截止日為110年11月24日(星期三)下午5時止(郵戳為憑)，歡迎市民踴躍報名，紙本郵寄請寄至以下地址：臺南市仁和路113巷39號，電子郵件報名請寄：renho@hcnllpa.org.tw或電洽06-2676508方主任。\n\n公共托育家園招生詳細規定與報名資訊，請至南市社會局網站「育兒資訊專區」查詢(https:\/\/sab.tainan.gov.tw\/News.aspx?n=21449&amp;sms=19554)。",
    "tags": "#社會 #公共托育家園"
}