{
    "published": "2023-12-26",
    "title": "回應臺南學甲爐渣案之不實指控",
    "department": "新聞及國際關係處新聞傳播科",
    "url": "https:\/\/www.tainan.gov.tw\/News_Content.aspx?n=13370&s=8609202",
    "content": "發稿單位:台南市政府\n發稿日期:112年12月26日\n\n有關總統候選人侯友宜競選辦公室針對臺南學甲爐渣案之不實指控，臺南市政府駁斥「根本是侯辦自我編織出來的幻想！」。臺南市政府指出，市府已於104年立即處理不法填埋爐碴案(副總統賴清德時任臺南市長) ，並採最嚴格的處分「廢止再利用機構身分」，同時要求業者挖除5萬5千餘噸不法爐碴。\n臺南市政府指出，廢止再利用業者身分已是最嚴厲的行政處分，卻被侯辦扭曲為「僅是避風頭」，甚是遺憾。質疑擁有「法學博士」、曾任「警大校長」的侯友宜，自請假市長職務後，是不是連基礎行政法學也還給老師了？\n市府說明，從賴清德前市長到黃偉哲市長，都依法予以不法業者最嚴厲懲處、強力要求業者將不法填埋爐碴清除，且密切配合檢調偵辦。此外，市府也把爐碴清除進度，公開放在市府環保快訊專區，供社會大眾檢視。\n市府表示，侯辦幕僚胡亂拼貼、任意曲解，恐有損侯友宜予人的刑警形象。呼籲應仔細求證、釐清事實真相。畢竟執政和創作文學小說，兩者是完全不同的。",
    "tags": "#學甲"
}