{
    "published": "2025-07-22",
    "title": "柳營、左鎮、關廟、安定等4區長宣誓  黃偉哲期許做好區政與市政溝通橋梁",
    "department": "新聞及國際關係處新聞傳播科",
    "url": "https:\/\/www.tainan.gov.tw\/News_Content.aspx?n=13370&s=8757014",
    "content": "發稿單位：新聞及國際關係處\n發稿時間：114年7月22日16：00\n發稿人：宋金燕 2991111＃8419\n\n台南市柳營區、左鎮區、關廟區及安定區等4區區長就職宣誓典禮於今（22）日市政會議舉行，由台南市長黃偉哲擔任監誓人。黃偉哲期許新上任區長能延續過去區長的發展基礎，到任後勇於承擔責任、積極任事，傾聽民意及掌握民眾需求，並且跟里長、議員之間能夠有充分的行政協調溝通，讓區政與市政密切結合。\n\n黃偉哲表示，區長是政府機關面對行政區域的第一線，也是救災搶災前線的指揮官，可謂是責任重大。黃偉哲期許新任區長持續扮演市府與市民之間的溝通橋樑，積極推動各項服務品質提升，讓民眾感受到市政溫度與效率。\n\n民政局說明，因應原柳營區、左鎮區及關廟區長退休及原安定區長調職所遺職缺，予以補實，連動調整1位區長職務，另有1位副區長、1位主任秘書及1位科長調陞區長。\n\n相關人員調整包括：柳營區公所劉發仲區長（原佳里區公所主任秘書）、左鎮區公所李燿州區長（原安定區公所區長）、關廟區公所陳必成區長（原永康區公所副區長）、安定區公所陳仁偉區長（原民政局自治行政科長）。",
    "tags": "#區長就職宣誓"
}