{
    "published": "2020-04-13",
    "title": "[標案案號]21090202[標案名稱]109年AI城市巡檢先導應用試驗計畫-城市行銷導覽[無法決標公告]",
    "department": "臺南市政府智慧發展中心數位創新組",
    "url": "https:\/\/www.tainan.gov.tw\/News_Content.aspx?n=4966&s=7655891",
    "content": "無法決標公告\n公告日:109\/04\/13\n[標案案號]21090202[標案名稱]109年AI城市巡檢先導應用試驗計畫-城市行銷導覽[招標方式]限制性招標(經公開評選或公開徵求)[新增公告傳輸次數]01[無法決標公告序號]001[原招標公告之刊登採購公報日期]109\/03\/03[是否依據採購法第106條第1項第1款辦理]否[機關代碼]3.95.100.3[機關名稱]臺南市政府智慧發展中心[單位名稱]臺南市政府智慧發展中心[機關地址]708臺南市安平區永華路2段6號12樓[聯絡人]許育誠[聯絡電話]06-2991111分機1384[傳真號碼]06-2985569[電子郵件信箱]merace1984@mail.tainan.gov.tw[是否複數決標]否[標的分類] &lt; 勞務類&gt; 842軟體執行服務[採購金額級距] 公告金額以上未達查核金額[原無法決標公告日期]109\/04\/13[無法決標公告日期]109\/04\/13[是否刊登公報]是[無法決標的理由]廢標[是否沿用本案號及原招標方式續行招標]是[附加說明]廠商未依通知到場辦理議價，且標價未進入底價，無法辦理決標。[評選委員]\n\t\t\t\t\t\t\t\t\t出席會議\n\t\t\t\t\t\t\t\t\t姓名\n\t\t\t\t\t\t\t\t\t職業\n\t\t\t\t\t\t\t\t\t與採購案相關之學經歷\n\t\t\t\t\t\t\t\t\t滿意度\n\t\t\t\t\t\t\t\t\t\t\t\t\t是\n\t\t\t\t\t\t\t\t\t陳佳欣\n\t\t\t\t\t\t\t\t\t嘉藥學校財團法人嘉南藥理大學助理教授\n\t\t\t\t\t\t\t\t\t經歷1：\t\t\t服務機關(構)名稱：嘉南藥理大學休閒保健管理系\t\t\t職稱：助理教授\t\t\t所任工作：休閒不動產開 發與管理、休 閒資源調查與 分析、休閒行 為學、休閒空 間規劃\t\t\t學歷：\t\t\t國立成功大學都市計劃研究所博士\n\t\t\t\t\t\t\t\t\t滿意\n\t\t\t\t\t\t\t\t\t\t\t\t\t是\n\t\t\t\t\t\t\t\t\t張郁靂\n\t\t\t\t\t\t\t\t\t私立崑山科技大學副教授兼空設系所主任\n\t\t\t\t\t\t\t\t\t經歷1：\t\t\t服務機關(構)名稱：崑山科技大學\t\t\t職稱：副教授\t\t\t所任工作：數位文化與歷史空間的多媒體暨虛擬實境應用、建築及室內空間設計之教學工作\t\t\t學歷：\t\t\t國立交通大學土木所建築組博士\n\t\t\t\t\t\t\t\t\t滿意\n\t\t\t\t\t\t\t\t\t\t\t\t\t是\n\t\t\t\t\t\t\t\t\t謝振益\n\t\t\t\t\t\t\t\t\t公務人員\n\t\t\t\t\t\t\t\t\t經歷1：\t\t\t服務機關(構)名稱：臺南市政府研究發展考核委員會\t\t\t職稱：副主任委員\t\t\t所任工作：副主任委員\n\t\t\t\t\t\t\t\t\t滿意\n\t\t\t\t\t\t\t\t\t\t\t\t\t是\n\t\t\t\t\t\t\t\t\t邱文志\n\t\t\t\t\t\t\t\t\t公務人員\n\t\t\t\t\t\t\t\t\t經歷1：\t\t\t服務機關(構)名稱：臺南市政府智慧發展中心\t\t\t職稱：組長\t\t\t所任工作：組長\n\t\t\t\t\t\t\t\t\t滿意\n\t\t\t\t\t\t\t\t\t\t\t\t\t是\n\t\t\t\t\t\t\t\t\t陳冠中\n\t\t\t\t\t\t\t\t\t公務人員\n\t\t\t\t\t\t\t\t\t經歷1：\t\t\t服務機關(構)名稱：臺南市政府智慧發展中心\t\t\t職稱：副主任\t\t\t所任工作：副主任\n\t\t\t\t\t\t\t\t\t滿意",
    "tags": "#智慧發展中心#109年#無法決標公告"
}