{
    "published": "2020-01-20",
    "title": "臺南市推動關懷享好家計畫  黃偉哲溫馨送暖 許孩子ㄧ個願望",
    "department": "新聞及國際關係處新聞傳播科",
    "url": "https:\/\/www.tainan.gov.tw\/News_Content.aspx?n=13370&s=7621257",
    "content": "（新聞及國際關係處發布）\n\n市長黃偉哲在環保局林淵淙局長及社會局朱棟主任秘書、下營區區長姜家彬陪同下，今(20)日前往下營區訪視43歲弱勢家庭湯先生，致贈藏金閣再生家具10件及臺南市庇護工場的春節禮盒，市議員陳秋宏、吳通龍也到場關心。\n\n黃市長聽說湯先生家中客廳桌及鐵製辦公桌損壞嚴重歪斜，沒有課桌椅及餐廳椅，小孩寫功課都直接趴在床邊，連吃飯也僅能坐在沙發上，覺得非常不捨，所以特別請環保局藏金閣將整理好的家具，贈送給湯家，讓小孩擁有張自己的課桌椅，可以專心做功課好好讀書，讓全家有椅子可坐在一起吃飯。現場可以看到湯先生的孩子很高興的在藏金閣的課桌椅上塗鴉，黃市長與小朋友互動中，得知孩子內心有一個小小的願望，就是想要變形金剛系列作品的「柯博文」商品，市長為了幫孩子實現這個願望，當場承諾將會贈送一個給他。\n\n黃偉哲市長表示，看到我們環保局、社會局共同關懷需要扶助的朋友，尤其是小朋友，他們是我們未來的希望，所以不能讓他們成長過程中有所缺憾跟失落，在歲末寒冬的時候，特別請環保局從藏金閣裡面挑出十件家具來提供他們真正所需要的，才是把愛心用在刀口上，再次呼籲一起透過環保局、社會局及勞工局的公益平臺，將珍貴的資源有效運用，幫助有需要的人。\n\n湯先生目前一家八口共住，湯先生原為高中老師，10年前因罹患多發性硬化症，領有肢體障礙重度證明，下肢無法行動且右手會痙攣抖動，湯先生父母年事已高皆退休、其母領有聽覺障礙證明，目前主要照顧1對國小1年級的雙胞胎小孩，生活經濟貧困，多仰賴社會福利補助維生。湯先生感性的說，經由社會局社工人員的協助轉介，接受由市長親自所致贈的藏金閣再生家具，全家感到很溫暖、很幸福，在農曆新年到來，讓家人有家具好使用，有家的幸福與安定感，非常感謝市政府團隊的用心。\n\n環保局表示，去年10月15日起環保局擴大辦理臺南市關懷享好家計畫，延續推動關懷弱勢社會公益，並將關懷視野擴大至低收入戶、中低收入戶、中低收老人生活津貼及身心障礙者，提供購置藏金閣平價家具優惠折扣服務，相關計畫服務內容及可挑選的家具，可至環保局藏金閣網站平價家具瀏覽https:\/\/epb2.tnepb.gov.tw\/yardsale\/mode02.asp?m=20191031115825&amp;t=menu，若有相關問題，可於上班時間撥打諮詢專線(06)2352011洽詢。",
    "tags": "#關懷弱勢享好家"
}