{
    "published": "2020-01-22",
    "title": "「哇賽！臺南好七淘  探險活寶」延展至2月底 阿寶老皮陪大家臺南過新年抽好禮",
    "department": "新聞及國際關係處新聞傳播科",
    "url": "https:\/\/www.tainan.gov.tw\/News_Content.aspx?n=13370&s=7621751",
    "content": "由臺南市政府觀光旅遊局結合卡通頻道在安平樹屋推出的「哇賽！臺南好七淘－探險活寶冬季冒險」活動展期原至12\/31止，卡通明星阿寶、老皮、泡泡糖公主及冰霸王的立體雕塑也一一現身安平樹屋讓大家萌拍，因應春節假期到臨，觀旅局特別將主題展區將延展至109年2月29日，並推出新春拍照加碼抽好禮的活動，歡迎大小朋友春節遊臺南，與卡通明星探險活寶們一起迎接鼠年！\n\n市長黃偉哲表示，新的一年開始，臺南新春活動不打烊且非常精采多元，市府臺南行春各大活動已陸續舉辦，為了讓大家輕鬆掌握臺南春節活動，特別建置了臺南行春網站，歡迎大家上網查詢與規劃臺南走春行程。\n\n臺南春節各地活動多元，觀光旅遊局表示，為迎接春節假期，「哇賽！臺南好七淘 探險活寶」將推出新春加碼抽活動，自即日起至2月9日止，民眾只要與探險活寶現身的17處景點之一的立牌合影(包括：安平樹屋、臺南火車站旅服中心、藍晒圖文創園區、臺南市鹽埕圖書館、奇美博物館、北門遊客中心、七股遊客中心、國立臺灣歷史博物館、雙春濱海遊憩區、新營文化中心、關子嶺大成殿、德元埤荷蘭村、葫蘆埤自然公園、無米樂旅遊服務中心、臺南左鎮化石園區、龜丹溫泉體驗池、臺南市南瀛天文館)，並於台南旅遊臉書粉絲團指定貼文上傳合照1張，就有機會抽中超萌6吋探險活寶玩偶(隨機出貨)及滑鼠墊1組，只有11個名額，趕快趁著新春拜年期間，和親朋好友相揪來臺南，跟隨探險活寶的旅遊足跡玩臺南合影留念！\n\n貼心提醒，年節期間注意交通管制資訊，避開擁塞路段，開心出門，平安回家。與各景點的探險活寶們拍照時，也請發揮公德心愛護展品，且為維護大家的安全，請不要攀爬展品及做出危險動作！春節相關活動訊息請上台南旅遊網(https:\/\/www.twtainan.net\/)或臺南行春入口網(http:\/\/2020tainan-newyear.com\/)查詢。\n\n\t探險活寶陪你過新年-新春加碼抽【活動日期】：即日起至2月9日止\n【參加方式】：即日起至2月9日前，於台南旅遊臉書粉絲團指定貼文留言處上傳1張與探險活寶打卡點&ldquo;合照&rdquo;(共17處景點，至少須選1處)，tag好友加上#探險活寶陪你過新年，就有機會可以抽中超可愛的6吋探險活寶玩偶（隨機出貨）及滑鼠墊1組，只有11個名額哦！！\n【拍照地點】：17處探險活寶立牌\/輸出物\n安平樹屋、臺南火車站旅服中心、藍晒圖文創園區、臺南市鹽埕圖書館、奇美博物館、北門遊客中心、七股遊客中心、國立臺灣歷史博物館、雙春濱海遊憩區、新營文化中心、關子嶺大成殿、德元埤荷蘭村、葫蘆埤自然公園、無米樂旅遊服務中心、臺南左鎮化石園區、龜丹溫泉體驗池、臺南市南瀛天文館。\n\n新聞聯絡人：\n觀光旅遊局觀光行銷科 丁玲琍科長 0921-607045\n觀光旅遊局觀光行銷科 李雅玲股長 0921-546848\n觀光旅遊局觀光行銷科 林淑芬科員 0912-923194",
    "tags": "#安平樹屋 #探險活寶"
}