{
    "published": "2021-11-22",
    "title": "南市汰換老車換新機   搭配購物節活動抽好禮",
    "department": "臺南市政府環境保護局空氣及噪音管理科",
    "url": "https:\/\/www.tainan.gov.tw\/News_Content.aspx?n=13371&s=7844366",
    "content": "臺南購物節熱烈進行中，市民朋友12月31日前淘汰96年6月30日前出廠老舊機車，換購電動機車或七期燃油車除享補助外，若購車的車行其營業登記在臺南，民眾還能參加購物節抽獎，單筆發票最高有500組抽獎序號，大獎有美宅、油電汽車等。汰換老舊機車有助於維空氣品質、還有補助又可抽獎，心動怎能不快行動。\n\n市長黃偉哲表示，臺南市近5年來已累積淘汰20萬餘輛車齡15年以上之高污染老舊機車。110年市政府提供淘汰老舊機車及換購低污染機車等5項補助方案，補助期間至110年12月31日截止。臺南購物節抽獎活動至明年3月5日止，有意汰換老舊機車的市民朋友，別錯過抽好康及為環保盡一分心力的機會。\n\n環保局表示，有意汰換老舊機車的市民朋友，唯有到在臺南市辦理營業登記的機車行選購，才能參加臺南購物節抽獎。每消費100元可獲1組抽獎序號，消費者購車後可到購物節網站填載營業地點登記於臺南市之購車統一發票，單筆發票最高可獲得500組抽獎序號，未抽中自動轉到下次抽獎，抽獎日期為每月5日，活動至111年3月5日止，總獎值超過2,000萬元。\n\n環保局長謝世傑指出，今(110)年淘汰老舊機車換購低污染機車補助，於111年1月10日前(含)完成申請程序，最高可享3.2萬元補助金，請市民朋友把握機會儘早申請；另外，今年也推出便民的「淘汰老舊機車換購低污染車輛加碼補助」線上申請系統，提供零時差服務，免出門也能申辦補助。相關補助申請及活動詳情請至「臺南市機車管制及汰舊換新補助資訊網」(網址:http:\/\/lowpoll.tnepb.gov.tw)查詢。有任何疑問，歡迎洽詢環保局06-3358262或3354359。\n\n承辦科長：楊朝全　電話：06-2686751#260\n承辦人員：陳佳宜　電話：06-2686751#354",
    "tags": "#南市汰換老車換新機   搭配購物節活動抽好禮"
}