{
    "published": "2022-07-30",
    "title": "8月1日至14日，台南市各級醫院及住宿型長照機構有條件開放探病（視）",
    "department": "臺南市政府衛生局綜合企劃科",
    "url": "https:\/\/www.tainan.gov.tw\/News_Content.aspx?n=13371&s=7910142",
    "content": "衛生局昨(29)日邀集南區指揮官、疾管署南區管制中心、各級醫院代表、社會局一同召開即時線上協調指揮中心（OLOCC）會議，做成「今（111）年8月1日至14日，台南市各級醫院及住宿型長照機構有條件開放探病（視）」決議，後續將視疫情發展滾動式調整相關規定。\n   8月1日起至14日，醫院有條件開放探病：包含加護病房、安寧病房、呼吸照護病房(含RCC)、精神科病房、慢性病房、兒童病房、身心障礙、病況危急或例外情形者；每日固定1時段，每名住院病人每次至多2名訪客為原則(例外情形不在此限)。\n   住宿型長照機構維持有條件開放探視，每位住民每日限探視1次，每位住民每次訪客至多3名(含兒童)，採預約制。若機構發生確定病例，暫停開放探視，直至機構內連續 7天無新增確定病例。    南市今(30)日新增1,717名COVID-19本土個案，統計自今(111)年1月1日至7月28日，台南市累計確診個案人數共314,133名，全年齡累計確診百分比為16.96%；已解除隔離301,817名、尚在隔離中12,316名。\n   統計至今(111)年7月29日，台南市COVID-19疫苗基礎劑第1、2劑、基礎加強劑、第1、2次追加劑涵蓋率分別為91.3%、84.9%、1.2%、69.7%及5.8%，總接種劑次4,693,773。6個月至4歲幼兒COVID-19疫苗第1劑涵蓋11.6%；5至11歲兒童第1劑涵蓋率85.04%、第2劑39.38%；12至17歲青少年第1劑涵蓋率94.82%、第2劑83.39%、追加劑59.89%。\n聯絡單位：臺南市政府衛生局防疫專線(06)2880180",
    "tags": "#本土個案說明 #衛生局 #臺南市"
}