{
    "published": "2022-06-03",
    "title": "台南市今(3)日新增6,620名COVID-19本土個案；端午連假期間務必落實防疫措施",
    "department": "臺南市政府衛生局綜合企劃科",
    "url": "https:\/\/www.tainan.gov.tw\/News_Content.aspx?n=13371&s=7897660",
    "content": "台南市今(3)日新增6,620名COVID-19本土個案，統計自今(111)年1月1日至6月2日，台南市累計確診個案人數共120,426名，已解除隔離77,280名、尚在隔離中43,146名。\n   6,620名個案中以20歲至49歲確診者人數3,440名最多，佔今日確診人數約5成2；10歲以下佔8.2%、10至19歲7.9%、50至59歲12.7%、60至69歲10.8%、70至79歲5.4%、80至89歲2.3%、90歲以上0.7%。\n   下週6月6日(週一)至12日(週日)南區松柏育樂中心及新化體育公園篩檢站將持續服務市民，除了鼻咽快篩、PCR採檢及陽性快篩試劑判讀，松柏育樂中心篩檢站也將提供看診及領藥服務，每日上午、下午限額各50名；衛生局提醒市民於端午連假期間務必落實防疫措施，保護自己也保護身邊親友的健康。\n聯絡單位：臺南市政府衛生局防疫專線(06)2880180",
    "tags": "#本土個案說明 #衛生局 #臺南市"
}