{
    "published": "2019-11-12",
    "title": "黑琵模型展七股開鑼了　黃偉哲歡迎親子來參觀",
    "department": "臺南市政府農業局森林及自然保育科",
    "url": "https:\/\/www.tainan.gov.tw\/News_Content.aspx?n=13371&s=5838922",
    "content": "素人工藝家李龍輝，花了三年多時間，自學製作國際明星鳥「黑面琵鷺」等各種冬候鳥模型，做工維妙維肖，相當吸睛，2019黑面琵鷺保育季特別邀請他來參展，展期從2019年12月1日起至2020年4月30日，台南市長黃偉哲歡迎雅好民眾一起來去七股特生中心黑面琵鷺展示館參觀。\n 李龍輝的黑面琵鷺模型作品中，黑面琵鷺一身雪白羽毛，有著一隻長長像湯匙的扁嘴巴，有的叼著魚，有的在嬉戲玩耍，牠的模樣相當逗趣。還有細細長長扁扁的嘴巴，模型作品栩栩如生，許多人都以為是黑面琵鷺的標本。\n 這些黑面琵鷺模型作品中，黑面琵鷺所站立的背景照片，是執行單位台南市生態保育學會副總幹事在南部地區黑面琵鷺棲息地方所拍攝的照片，搭配起來更有生動，以及真實臨場感。\n 至於李龍輝的黑琵模型創作過程，他表示，三年前，他和朋友相約到鰲鼓溼地賞鳥，順手買了兩隻反嘴鴴和高蹺鴴的模型回家，從此便開始研究製作各種冬候鳥模型，尤其對於黑面琵鷺更感興趣。他說，要製作模型的過程，必須先了解各種鳥類的特徵外，製作過程也需要細心與耐心，才會有好作品。\n 臺南市政府農業局長李朝塘表示：「李龍輝製作的黑面琵鷺模型，栩栩如生、唯妙唯肖，證明他對於黑面琵鷺的觀察非常入微，因為他一直很用心，黑面琵鷺也從亞成鳥的非繁殖羽做到成鳥的繁殖羽」，令人嘆為觀止。\n 目前正是觀賞黑面琵鷺的旺季，市長黃偉哲歡迎全國民眾除了來七股黑面琵鷺保護區觀賞黑面琵鷺，也可以來黑面琵鷺展示館觀賞黑面琵鷺的鳥類模型，遊客不僅可以親近冬候鳥黑面琵鷺，也能進一步認識生態保育的重要性，持續愛護黑面琵鷺。\n\n新聞連絡人：森林及自然保育科 朱健明 電 話：06-6321731",
    "tags": "#生態保育"
}