{
    "published": "2024-04-06",
    "title": "遏止網路犯罪與防駭！臺南市政府與法務部調查局簽署MOU",
    "department": "臺南市政府智慧發展中心",
    "url": "https:\/\/www.tainan.gov.tw\/News_Content.aspx?n=13371&s=8629207",
    "content": "　　臺南市政府及法務部調查局臺南市調查處為提升資安聯防之情資共享及鑑識能量，於近日合作簽署「國家資通安全聯防與情資分享合作備忘錄MOU）」，共同建構城市資安防禦體系。\n　　黃偉哲市長表示，智慧城市物聯網設備在當今社會廣泛應用，但也帶來了資訊安全的風險，為確保政府運作和社會安定，各機關嚴禁採購危害國家資通安全產品；同時，各機關也要加強管理社群平台帳號，防止社交工程攻擊和不當訊息的傳播。今臺南市政府與調查局簽署合作備忘錄建立密切聯繫管道，可藉由資安情資快速通報、資安攻擊事件即時偵辦、資安事件調查結果應變處置及案例分享交流等合作模式，以保障社會資訊安全。\n　　研考會陳主委表示，臺南市政府積極強化各項資安工作，持續爭取中央資安補助預算，落實資訊資源向上集中、終端設備資安偵測及持續盤點資訊資產，掌握高風險漏洞，即時修補，並與雲林縣、嘉義縣、嘉義市等區域縣市建立資安區域聯防，及加入國家資安資訊分享與分析中心(NISAC)會員，落實各項國家資安政策及防護措施。\n　　該合作案將在資安事件發生時保留駭客入侵跡證，並主動通報調查局臺南市調查處，以司法調查權針對源頭進行追溯，並藉由情資共享，提升行政機關資安防護量能；此舉共建事前預防、事中調查及事後回饋之資安聯防生態系，塑造安全、可信賴之智慧城市。\n新聞聯絡人：研考會-智慧發展中心 主任 陳冠中 06-3901274、0982-033933研考會-智慧發展中心 分析師 李佳璋 06-2991111分機1181",
    "tags": "#國家資通安全聯防與情資分享合作備忘錄"
}