{
    "published": "2022-03-26",
    "title": "黃偉哲力促成大沙崙醫療創新園區　蘇揆拍板下半年動工",
    "department": "臺南市政府經濟發展局產業發展科",
    "url": "https:\/\/www.tainan.gov.tw\/News_Content.aspx?n=13371&s=7881612",
    "content": "行政院長蘇貞昌今(26)日視察沙崙醫療創新園區預定地，宣布該項建設正式啟動，預計最快下半年動工第一期工程；黃偉哲市長感謝中央支持，具備綠能永續、智慧資安、AI、5G、大數據與量子科技等先進技術的沙崙智慧綠能科學城，接下來搭配此園區的智慧精準醫療，正是台灣在後疫情時代走向世界的關鍵力量，「來台南沙崙，看見未來的台灣！」\n\n黃偉哲市長表示，臺南近四年逐步落實蔡總統的大南方大發展、5+2 創新產業、六大核心戰略產業等政策，而市府團隊攜手成功大學歷經近 10 次北上開會爭取，加上在地立委協助，特別是王定宇委員積極與會，沙崙醫療創新園區終在去年底獲得行政院核定，感謝賴副總統關心期許，更感謝蘇院長支持及李孟諺秘書長居中協調，市府團隊將盡力讓全台第一個醫療服務創新園區盡早啟用。\n\n黃偉哲市長介紹「成大沙崙醫療創新園區」，將是全臺第一處以醫療服務結合人工智慧與大數據分析，能讓新豐區每萬人平均一般病床數提高至 160%，弭平醫療資源落差，未來服務可望擴及南科、善化、新市、永康甚至北高雄；此外，受衛福部託付設立的「南臺灣兒童醫療中心」，亦將嘉惠南部兒童。\n\n成功大學蘇慧貞校長指出，沙崙醫療園區將分兩期開發，除醫院本體，預計還有兒童醫療中心、特色醫療中心、臺灣新南向衛生訓練中心、沙崙國家級傳染病中心及大數據中心等五大中心，沙崙醫療園區將導入 大數據、AI、5G等技術，全力佈局下一世代「精準醫療」策略，打造南部地區戰略型醫療中心。\n\n經發局長陳凱凌說明，市府攜手成大發展沙崙，除共同規劃「沙崙智慧 綠能科學城 2.0 計畫」，去年並結合歐洲商會及國內企業簽署「沙崙智慧產業創新聯盟」合作備忘錄，成為台南淨零碳排之永續發展示範區， 專精前瞻技術的沙崙不同於一般工業區，將是全台智慧綠能新市鎮典範。",
    "tags": "#黃偉哲力促成大沙崙醫療創新園區 # 蘇揆拍板下半年動工"
}