{
    "published": "2026-05-12",
    "title": "永康區西灣活力秀 希望社區最有勁 長者展現活力與創意風采",
    "department": "臺南市政府衛生局綜合企劃科",
    "url": "https:\/\/www.tainan.gov.tw\/News_Content.aspx?n=13371&s=8813693",
    "content": "臺南市永康區西灣社區關懷據點長期致力於長者照顧服務，以「活力」與「創新」為發展核心，推動「第三家庭」自主管理模式成效卓著。在理事長郭惠英帶領下，結合據點主任張明慧的專業規劃，以及志工隊長黃光明與全體志工的熱心投入，成功營造出一個兼具學習、互動與展演功能的溫馨社區平台。\n&ensp;&ensp;&ensp;&ensp;為展現據點推動成果，西灣社區近日舉辦「永康區西灣─希望社區最有勁」活力秀初選，充分展現長者的自信與活力。參與長者從過去的被動參與，逐步轉變為主動投入，不僅勇於站上舞台，更透過精采演出，贏得現場觀眾熱烈掌聲，具體實踐「活到老、學到老」的精神。\n&ensp;&ensp;&ensp;&ensp;本次演出以「大王叫我來巡山」為靈感，創意結合現代生活情境，長者們化身為勤奮工作的「小妖精」，透過巡視任務、處理事務等橋段，生動呈現基層上班族的日常樣貌。節目內容融入查詢快遞、業務巡檢等生活化元素，以幽默詼諧方式演繹職場辛勞與堅持，讓觀眾在笑聲中產生深刻共鳴。\n&ensp;&ensp;西灣社區表示，透過多元化團康活動與創意展演，不僅有效促進長者身心健康，也提升其自我認同與社會參與感。未來將持續以創新思維推動社區發展，讓關懷據點成為長者的「第三個家」，營造互助共融、充滿希望的在地社區。\n&ensp;&ensp;臺南市政府衛生局表示，隨著高齡社會來臨，推動社區活化與提升長者參與已成為重要課題。透過在地關懷據點辦理多元健康促進與社會參與活動，不僅有助於延緩失能與促進身心健康，更能增進長者人際互動與生活成就感，實踐在地老化與健康老化目標。西灣社區以創新展演結合社區關懷，不僅展現長者活力，也充分發揮社區凝聚力，為打造高齡友善城市樹立良好典範。\n&ensp;&ensp;「希望社區最有勁」不僅是一句口號，更是西灣社區長者以實際行動展現的生命力。誠摯邀請社會各界持續關注與支持在地社區發展，共同見證長者綻放無限可能。",
    "tags": "#長者展現活力與創意風采 #西灣活力秀 #衛生局 #臺南市"
}