{
    "published": "2021-12-05",
    "title": "意鳴津人鹽水嘉年華熱鬧登場 遊月津玩AR遊戲抽大獎",
    "department": "臺南市政府經濟發展局商業科",
    "url": "https:\/\/www.tainan.gov.tw\/News_Content.aspx?n=13371&s=7850524",
    "content": "臺南市政府、鹽水區公所與月津港文化觀光商圈發展協會聯手辦理「2021意鳴津人鹽水嘉年華」，活動於今(5)日在鹽水區公所前中山路封街舉辦，黃偉哲市長親臨現場為現場攤商加油打氣，期望藉由展售的方式讓更多人了解鹽水美食與文化，活動主題包含「鹽水特色市集」、「集章摸彩」、「手作美食體驗」、「AR闖關遊戲」、「無二不賣－二手公益市集」及「特色表演」等，內容精彩多元吸引遊客參加。\n\n  市長黃偉哲表示，鹽水有豐富多元的在地特色，公所與商圈協會為了行銷店家，共同推出的「集章摸彩」活動，讓遊客以趣味簡單的集章方式體會鹽水美食及風情，獎項包含多項好禮。而搭配集章活動推出搶先開跑的「意鳴津人DM折扣禮活動」，讓民眾可以憑活動DM於指定期間到特約合作店家可以享有專屬優惠，藉此帶動商圈買氣，也歡迎大家平時常來鹽水，體驗小鎮之美。\n\n  鹽水區長陳文琪表示，公所與在地商圈為了推動鹽水商圈行銷，自106年合作發想首辦鹽水商圈意麵節活動，藉由在地美食節慶行銷鹽水商圈，帶動觀光產業的發展，今年更首度推出「意鳴津人鹽水嘉年華」活動，除鹽水意麵美食品嚐，也結合科技AR遊戲體驗及二手市集義賣公益活動，希望能讓遊客透過嘉年華的精彩內容，認識鹽水豐富多元的特色。\n\n  經發局陳凱凌局長說，今年鹽水嘉年華活動結合各特色店家及多元美味的鹽水特產搭配專屬的優惠，歡迎大家一起來探索鹽水美食的奧妙。另外也提醒大家，臺南購物節活動至明年3月5日止，活動期間於臺南店家消費滿100元發票上活動官網參加抽獎，您將有機會入主全新美屋。(詳情請上臺南購物節網站查詢https:\/\/tainanshopping.tw\/)。",
    "tags": "#意鳴津人鹽水嘉年華熱鬧登場 遊月津玩AR遊戲抽大獎"
}