{
    "published": "2023-09-11",
    "title": "「新港社大道與南科聯絡道路口轉向改善工程」年底完工  可望疏解南科聯外交通",
    "department": "新聞及國際關係處新聞傳播科",
    "url": "https:\/\/www.tainan.gov.tw\/News_Content.aspx?n=13370&s=8589198",
    "content": "發稿單位：工務局\n發稿時間：112年9月11日09:05\n\n新港社大道與南科聯絡道路口轉向工程歷經兩年施工，將於112年底完工，日前相關單位現場會勘，初步敲定將做整體號誌及路側設備更新，並以即時監控車流調整號誌時間，以疏解車流，通車後可望大幅改善南科上班尖峰時間交通壅塞問題。\n\n因應南科就業人口成長的交通需求，建構更完整的交通路網，市府向內政部營建署爭取辦理「新港社大道與南科聯絡道路口轉向改善工程」，工程總經費約3.3億元，道路採立體化車道設計，工程長度約1公里，寬30公尺，橋梁長度約340公尺，於110年8月開工，預計本(112)年底完工。\n\n為發揮工程最大效益，工務局日前邀集內政部營建署南區工程處、南科管理局、交通局、新市區公所等單位到現場會勘，研商交通引導號誌等配置問題，由於完工後新港社大道往南科園區方向為四車道(高架2車道、平面2車道)，初步決定交通號誌採輪放方式，以避免下高架車流與平面道路車流交織造成碰撞影響行車安全，未來也將做整體號誌及路側設備更新，並以即時監控車流調整號誌時間，以疏解車流。\n\n工務局強調，南科聯絡道路口轉向工程完工後，可提供進南科園區更便捷道路，減輕新港社大道與南科聯絡道路口轉向車流壓力，可望大幅改善南科上班尖峰時間交通壅塞問題。",
    "tags": "#工務 #新港社大道 #南科聯絡道"
}