{
    "published": "2023-09-01",
    "title": "登革熱防治中心帶領慈濟及社區志工自製簡易產卵誘集桶，幫助民眾輕鬆滅蚊保健康!",
    "department": "新聞及國際關係處新聞傳播科",
    "url": "https:\/\/www.tainan.gov.tw\/News_Content.aspx?n=13370&s=8586150",
    "content": "發稿單位:衛生局\n發稿日期:112年9月1日\n臺南市截止今日下午3點經疾病管制署研判確診162例本土登革熱確診病例，目前累積本土病例為3,220例，今日162例分布狀況為安南區51例，東區31例，永康區25例，南區22例，北區15例，中西區7例，歸仁區4例，關廟區3例，安平區、仁德區、新市區及安定區各1例，年齡介於1歲以下至93歲，156例是由診所或醫院通報確診，6例由防治中心擴大採檢發現，防疫人員已立即進行個案居住地及工作地戶內外化學防治作業，同時加強動員擴大孳生源清除及病媒蚊密度調查等工作，並進行附近住戶健康監視及診所發燒症狀就醫民眾的追踨關懷等防疫措施，期能降低疫情擴散風險。\n\n 因應安南區溪墘里、幸福里、安富里及海佃里登革熱疫情持續升溫狀況，專家建議可透過於家戶內陰暗處，如衛浴廁、廚房與客廳角落等，設置簡易產卵誘集桶方式，降低病媒蚊成蚊密度，以減少社區傳播風險，有鑑於此，南市衛生局立即緊急採購相關材料，如黑色育苗軟盆、飲料胖胖杯、黏蟲紙、16目紗網及各式工具等，今明兩日由登革熱防治中心同仁帶領慈濟志工與社區志工們加緊趕工，共同DIY製作4,000個簡易產卵誘集桶，預計發給上述里別之民眾放置於家戶內，誘殺病媒蚊成蚊，今日防治中心蘇世斌主任亦特別到現場為志工們加油打氣，並向里長及志工們說明如何透過誘殺桶來消滅家中病媒蚊成蚊；蘇世斌主任表示，近期時有強降雨發生，雨後形成許多積水容器，可能增加病媒蚊孳生風險，民眾可透過多重防蚊措施，如穿著長袖衣褲、使用捕蚊燈、電蚊拍或是DIY製作簡易產卵誘集桶等方式，多管齊下降低家中病媒蚊密度，以避免被病媒蚊叮咬，保護自身及家人健康，南市衛生局網站上皆有簡易產卵誘集桶DIY教學影片，網址: https:\/\/health.tainan.gov.tw\/page.asp?mainid=CB1DC419-4733-4717-850E-9977542D8FC9，參照影片步驟即可輕鬆完成，還可親子同樂共同DIY，不但可達成殺死家戶內病媒蚊的效果，還能寓教於樂，鼓勵孩童認識病媒蚊，讓登革熱防疫從小紮根。現場志工們亦踴躍加入製作產卵誘集桶行列，大家齊心協力為社區防疫共同努力，認真投入精神令人動容。\n\n 另經疾病管制署分析，本市部分個案隱藏期較長可能原因，推測因本市流行的是第一型登革病毒，症狀較不明顯，可能導致民眾輕忽致有延遲就醫情況，蘇世斌主任再次提醒，請民眾務必提高警覺，如有發燒、頭痛、眼窩痛、肌肉關節痛或出疹等疑似症狀應儘速就醫，勿自行服用成藥，本市37區衛生所及全市近400家登革熱NS1快篩合約院所皆有提供登革熱快篩採檢服務，請有疑似登革熱症狀且有上述登革熱流行區域活動史的市民應儘速主動前往接受篩檢。\n\n臺南市政府登革熱稽查大隊持續落實社區孳生源清除及稽查任務，本週於安南區共調查2,198戶、其中陽性戶5戶，查獲322個積水容器、7個陽性容器，衛教1,186人次。為能積極找出潛在病例，鼓勵民眾主動前往篩檢，南市37區衛生所皆有提供登革熱快篩採檢服務，如有疑似症狀民眾前往衛生所篩檢即贈送精美宣導品一份。本市登革熱NS1快篩合約院所相關資訊請參閱臺南市政府登革熱防治中心網頁https:\/\/gov.tw\/zv9 或06-3366366防疫專線。",
    "tags": "#登革熱"
}