{"8625821":"https:\/\/www.tainan.gov.tw\/News_Content.aspx?n=13373&s=8625821","8626115":"https:\/\/www.tainan.gov.tw\/News_Content.aspx?n=13370&s=8626115","8626117":"https:\/\/www.tainan.gov.tw\/News_Content.aspx?n=13371&s=8626117","8626120":"https:\/\/www.tainan.gov.tw\/News_Content.aspx?n=13370&s=8626120","8626121":"https:\/\/www.tainan.gov.tw\/News_Content.aspx?n=13370&s=8626121","8626130":"https:\/\/www.tainan.gov.tw\/News_Content.aspx?n=13371&s=8626130","8626137":"https:\/\/www.tainan.gov.tw\/News_Content.aspx?n=13371&s=8626137","8626169":"https:\/\/www.tainan.gov.tw\/News_Content.aspx?n=13371&s=8626169","8626178":"https:\/\/www.tainan.gov.tw\/News_Content.aspx?n=13370&s=8626178","8626192":"https:\/\/www.tainan.gov.tw\/News_Content.aspx?n=13371&s=8626192","8626212":"https:\/\/www.tainan.gov.tw\/News_Content.aspx?n=13371&s=8626212","8626213":"https:\/\/www.tainan.gov.tw\/News_Content.aspx?n=13371&s=8626213","8626215":"https:\/\/www.tainan.gov.tw\/News_Content.aspx?n=13371&s=8626215","8626219":"https:\/\/www.tainan.gov.tw\/News_Content.aspx?n=13370&s=8626219","8626221":"https:\/\/www.tainan.gov.tw\/News_Content.aspx?n=13370&s=8626221","8626235":"https:\/\/www.tainan.gov.tw\/News_Content.aspx?n=13370&s=8626235","8626238":"https:\/\/www.tainan.gov.tw\/News_Content.aspx?n=13370&s=8626238","8626241":"https:\/\/www.tainan.gov.tw\/News_Content.aspx?n=13370&s=8626241","8626243":"https:\/\/www.tainan.gov.tw\/News_Content.aspx?n=13371&s=8626243","8626244":"https:\/\/www.tainan.gov.tw\/News_Content.aspx?n=13370&s=8626244","8626245":"https:\/\/www.tainan.gov.tw\/News_Content.aspx?n=13370&s=8626245","8626254":"https:\/\/www.tainan.gov.tw\/News_Content.aspx?n=13370&s=8626254","8626289":"https:\/\/www.tainan.gov.tw\/News_Content.aspx?n=13371&s=8626289","8626318":"https:\/\/www.tainan.gov.tw\/News_Content.aspx?n=13370&s=8626318","8626503":"https:\/\/www.tainan.gov.tw\/News_Content.aspx?n=13370&s=8626503"}