{
    "published": "2020-03-16",
    "title": "黃偉哲重視今年黑琵未換繁殖羽異常現象，農業局召開會議釐清成因",
    "department": "臺南市政府農業局森林及自然保育科",
    "url": "https:\/\/www.tainan.gov.tw\/News_Content.aspx?n=13371&s=7650435",
    "content": "台南市長黃偉哲重視黑面琵鷺未換繁殖羽的異常現象，指示農業局擬定黑面琵鷺保育措施，於今(16)日邀請林務局、嘉義林區管理處、特有生物研究保育中心、台江國家公園管理處、高雄市政府農業局、嘉義縣政府農業處、台南市動物防疫保護處、慈愛動物醫院、台南市野鳥學會、台南市生態保育學會、台灣黑面琵鷺保育學會及台南市野生動物保育學會等產、官、學單位，召開「黑面琵鷺未換繁殖羽」與「七股頂山棲息地數量減少」討論會，望釐清發生之原因，作為擬定保育措施之依據。\n 農業局長謝耀清表示，今日會議參與單位與個人發言踴躍，並作成多項結論，對未來黑面琵鷺保育有莫大幫助。\n 另近年常有流浪犬追趕黑面琵鷺及其它保育類野生動物事件之發生，為減少事件發生頻率，台南市政府農業局、高雄市政府農業局及嘉義縣政府農業處皆認為在公有領域的土地如國家風景區、濕地、林班地、海堤、水庫等，基於保護流浪動物及野生動物的立場，各權管單位應有防止其受困、受虐、攻擊鳥類及群聚追咬傷人之積極作為，並立法禁止在該等區域內餵食流浪動物及野生動物，保障動物生存權。\n　 在「黑面琵鷺未換繁殖羽」議題之結論有三點：１黑琵繁殖羽應屬生理問題，且依據往年經驗，於南風吹起時才會大量換羽；另亞成鳥如無繁殖需求，亦無換羽需求；請各NGO團體在平日調查及觀測時持續觀察，作為長期觀測統計資料分析；並將相關訊息提供農業局及台江國家公園管理處研議處理方針。２保護區棲地營造及水位調控，建請台江國家公園管理處在現有基礎調查案內納入，及落實研究及實務並重。３請中央權管單位加強公有領域流浪犬管理，以減少流浪犬追趕黑琵事件發生；並建議成立委辦計畫委託地方政府辦理，減少流浪犬干擾野生鳥類覓食及棲息。\n 在「七股頂山棲息地數量減少」議題有二項結論：１本年2月初寒流來襲造成七股頂山棲息地大量魚類死亡，初估約10萬尾，黑面琵鷺為生計，飛往他處覓食；依據105年霸王級寒流造成本市大量虱目魚死亡，亦未影響黑琵北返及食源，爰七股頂山棲地數量減少應非屬食源不足所引起。２為增加七股頂山棲地食源，農業局會協調第六河川局協助水門管理，希望每周利用漲退潮時間打開水門一次，引進魚源及調換水質，提升本棲地黑面琵鷺及其它水鳥食源。\n 專家們請轄內保育團體及志工於黑琵度冬期間，若發現黑面琵鷺個體其活動力弱，無法飛翔甚至蹲坐地面、嘴巴微張、軟頸、翅膀下垂等情形，立即通知本局〈聯絡電話06-6321731〉，或立即下灘搶救並送慈愛動物醫院醫治，縮短救援及救治時間，黑面琵鷺存活率相對提高。\n新聞連絡人：森林及自然保育科 朱健明 電 話：06-6321731",
    "tags": "#黑面琵鷺"
}