{
    "published": "2023-08-15",
    "title": "8.18(五)及8.19(六)勞工局職訓就服中心將辦理「昕叡創能有限公司-GOGORO單一現場徵才活動」，歡迎求職民眾踴躍參加!",
    "department": "臺南市政府勞工局職訓就服中心",
    "url": "https:\/\/www.tainan.gov.tw\/News_Content.aspx?n=13371&s=8582148",
    "content": "為打造黃偉哲市長「希望家園」的施政願景，勞工局職訓就服中心積極辦理各項就業徵才活動，並因應產業求才需求，勞工局職訓就服中心於112年8月18日(五) 及8月19日(六)10:00假昕叡創能-台南健康門市(臺南市中西區健康路一段68號1樓)辦理「昕叡創能有限公司-GOGORO單一現場徵才活動」，提供16個職缺，歡迎求職民眾踴躍報名參加，洽詢電話:06-2930785。\n※面試時間：09:50-10:00報到\n         10:00-12:30公司說明會、產品體驗、職場參訪\n※面試地點：昕叡創能-台南健康門市(臺南市中西區健康路一段68號1樓)\n※報名方式：每場次參加名額有限，請採事先報名，請點選報名網址https:\/\/forms.gle\/BULLkVq8kB8K8xVB7預約報名\n※報名日期：即日起至112\/8\/18(五)下午17:00截止。\n※職缺名稱及人數、薪資：\n RS-門市銷售代表4名\/月薪28,000元起。\n RS-門市儲備幹部4名\/月薪34,000元起。\n AS-維修服務工程師4名\/月薪28,000元起。\n AS-維修儲備幹部4名\/月薪40,000元起。\n※工作內容：智能電動車推薦銷售、精品配件推薦銷售、顧客關係維繫服務、\n 顧客使用問題解決、團隊事務與後勤作業。\n※學歷：專科以上\n※工作時間：11:00-21:00(中間休息2小時)\n※工作地點：臺南市全區(依公司分發)\n歡迎求職者於8\/18下午17：00前線上報名，活動職缺之薪資明確標示於徵才現場。\n(發稿人：勞工局職訓就服中心 電話06-2930785)",
    "tags": "#8.18(五)及8.19(六)勞工局職訓就服中心將辦理「昕叡創能有限公司-GOGORO單一現場徵才活動」，歡迎求職民眾踴躍參加!"
}