{
    "published": "2020-12-04",
    "title": "牙周照護，您應該要知道的三兩事",
    "department": "",
    "url": "https:\/\/www.tainan.gov.tw\/News_Content.aspx?n=13371&s=7731916",
    "content": "「哎呀!怎麼又流血了，牙齦也腫腫的不舒服，大概是熬夜太累了」、「今天的牙齒怪怪的，感覺脹脹的」，這些在您心中的三兩事，是不是每隔一段時間，就困擾著您呢?\n牙周疾病是國人常見的疾病，且大多數的人未曾注意過，但研究顯示在30歲以上的成人，約有50% 以上患有牙周相關疾病，而65歲以上的長者比例則更高。其實牙周病就像蛀牙一樣，隨著時間與個人的輕忽逐漸成形病灶，早期的症狀包含了牙齦紅腫或發炎，平時刷牙時會有血絲，甚至平時就會有不自主的流血，並逐漸破壞牙周韌帶及牙齦組織的退化及流失，最終造成牙齒逐漸鬆動，演變為牙周病及後續的牙齒脫落等問題。\n然而保持良好的衛生習慣及口腔清潔，則是避免牙周疾病的不二方法，包含避免菸檳酒等不良習慣、餐後潔牙等等，都是最基本照護，此外，定期檢查更是重要，每半年至牙科診所接受的口檢或洗牙，替自己的牙齒進行全身健康檢查。但是如果真的有牙周疾病的發生也不要太過緊張，全民健康保險中亦有提供「牙周病統合照護」治療計畫，讓牙醫師替您進一步地進行後續牙周病治療，維持齒列的健康喔。\n最後要提醒各位市民，有健康的牙齒才能有好品質的生活，提供大家一個好口訣，護齒好簡單，健康123：第1是要記得餐後潔牙，第2是使用適當的潔牙工具，如含氟牙膏、牙線等，第3當然是定期口腔檢查，千萬不要忘記了喔!!\n\n\n發稿人：國民健康科 鄧嘉仁\n連絡電話：06-6357716（東興辦公室）轉257\n06-2679751（林森辦公室）轉268",
    "tags": "#牙周 #口腔照護.衛生局"
}