{
    "published": "2023-10-09",
    "title": "白河市場雙十消費樂 好運8倍送",
    "department": "臺南市市場處經營二科",
    "url": "https:\/\/www.tainan.gov.tw\/News_Content.aspx?n=13371&s=8594969",
    "content": "為同慶雙十節並刺激市場買氣及人潮，南市府於112年10月9日上午在白河公有零售市場推出雙十節快閃促銷活動，市民朋友陪著媽媽一起到白河菜市場採買消費，試手氣拿好康，放大銅板50元市場抵用券，幸運兒並獲得8倍面額之抵用券，現場民眾熱烈排隊響應，整個市場一大早就熱鬧滾滾。\n黃偉哲市長說目前登革熱疫情嚴竣，請市民朋友務必持續做好「巡、倒、清、刷」，全力減少登革熱病媒蚊之孳生，如需外出也儘可能穿著長袖、長褲，降低被病媒蚊叮咬之機會，希望在市府與全體市民一起努力下，登革熱疫情可儘快解除，讓生活可以回歸常態。\n經發局長林榮川表示，各公有市場在新冠肺炎、登革熱疫情期間皆全力配合市府防疫政策，白河市場並積極配合中央及市府各項振興措施，於春節期間舉辦開春迎財神促銷加碼抽福袋活動，雙十國慶連假再度辦理消費抽獎促銷活動，市府團隊持續努力，在顧防疫及拚經濟上，一起再加油。\n市場處長陳豪吉也說，「市場夜市銅板快閃夠購go」快閃促銷活動，於去年度推出舉辦即受到熱烈迴響，今年度本府也將持續於各地市場及傳統夜市接力舉辦快閃活動，並依市場規模快閃送出數百份50元的市場夜市券，增加市場及夜市收益外，匯聚人氣，刺激經濟。",
    "tags": "#白河市場，雙十，促銷，50元券"
}