{
    "published": "2023-10-22",
    "title": "六度封王，臺南市軟式網球代表隊再度拿下全國運動會金牌  舉重方莞靈破大會及全國紀錄",
    "department": "新聞及國際關係處新聞傳播科",
    "url": "https:\/\/www.tainan.gov.tw\/News_Content.aspx?n=13370&s=8597464",
    "content": "發稿單位：112年全國運動會籌備處\n發稿時間：112年10月22日22:00\n\n112年全國運動會於臺南市展開第二天賽事，臺南市在強項軟式網球中不負眾望，順利在男女團體賽創下豐碩戰果，雙雙奪得金牌，男子組余凱文、林韋傑、郭建群、陳宗彣、陳柏邑、陳郁勲及歐子鴻及女子組吳佳穎、洪榆姍、徐巧楹、郭千綺、黃詩媛、詹佳欣、薛意如分別寫下六連霸及三連霸的紀錄，而舉重精靈方莞靈於抓舉82公斤破大會紀錄、挺舉105公斤破大會紀錄及平全國紀錄、總和187公斤破全國紀錄。另田徑鉛球男子組馬皓瑋亦以18.21的成績獲得金牌順利取得二連霸。身兼籌備處召集人的黃偉哲市長除在第一時間恭賀選手外，也指派籌備會執行長陳良乾局長到各競賽場地為選手加油，期待接下來4天的賽事中，選手們能趁勝追擊，為臺南市締造好成績。\n \n身兼籌備處召集人的黃偉哲市長表示，除軟式網球、舉重及鉛球獲得佳績之外，本市高爾夫女子團體賽繼110年為臺南市獲得金牌後，在本屆全運會亦順利摘金取得二連霸，其中個人女子組吳純葳、黃品菲更是分別獲得金牌及銀牌，男子組黃仁杰獲得銅牌，臺南市選手表現大放異彩，值得肯定，不僅讓來自其他縣市運動選手看見臺南選手的實力，也讓臺南在體育舞台上發光發熱。\n　　\n籌備會執行長陳良乾表示，臺南市選手的養成，不僅是教練的付出與指導，從培訓的過程中學校行政端的支持亦是不可或缺的一環。選手個人的努力有目共睹，藉由這份榮耀的肯定，不但能鼓勵選手往自己專長的運動領域持續精進，亦能提升本市體育發展之品質，以期未來臺南市能培育出更多優秀的體育人才，成為體壇的明日之星。\n \n本次賽會截至今日為止，臺南市共獲得19金22銀23銅，田徑、桌球、跆拳道、游泳、網球等奪牌重點項目正如火如荼進行中，期待選手們能再度締造好成績。",
    "tags": "#全國運動會"
}