{
    "published": "2024-05-04",
    "title": "守護海洋 南市水環境志工漁光島淨灘",
    "department": "臺南市政府環境保護局水域及毒物管理科",
    "url": "https:\/\/www.tainan.gov.tw\/News_Content.aspx?n=13371&s=8635677",
    "content": "臺南市政府環保局5月4日在安平區漁光島舉辦淨灘活動，包括水環境守護志工、企業及社區民眾共百餘人熱烈響應，大家頂著豔陽捲袖撿垃圾，盡一已之力守護海洋與環境，兩小時共清出45.4公斤垃圾及22公斤資源回收物。\n\n淨灘活動自上午8時許展開，清理範圍包括海岸線及防風林長約600公尺，清出的垃圾經過分類，統計以寶特瓶、玻璃瓶、保麗龍、菸蒂、鋁箔包等常見生活廢棄物居多，更利用篩網發現不少隱藏在沙灘裡的塑膠微粒，可見塑膠廢棄物的污染無所不在。\n\n活動現場亦進行海洋環境教育及生活污水污染源頭減量宣導，向市民及遊客宣導海洋守護的重要性，呼籲大家從生活中落實源頭減量減塑，讓海洋生態環境永續發展。\n\n局長許仁澤指出，愛地球就從日常生活小細節做起，例如垃圾減量、減少使用一次性物品、外出遊玩時自備水壺或環保袋等，並隨手帶走垃圾，共同為地球永續盡一份心力。\n\n海洋生態的永續發展需市民一同守護，環保局籲請民眾如果發現海洋環境污染，請立即撥打公害陳情專線0800-066-666或環保局報案專線06-6572916轉2222通報，將儘速派員應變處理。\n\n承辦單位：水域及毒物管理科\n承辦科長：翁崑沅　電話：06-6572813#2300\n承辦人員：彭福珍　電話：06-6572813#2330",
    "tags": "#守護海洋 南市水環境志工漁光島淨灘"
}