{
    "published": "2023-07-23",
    "title": "南巿永康社福中心臺南貨櫃公園闖關趣 黃偉哲邀請親子共遊FUN暑假",
    "department": "新聞及國際關係處新聞傳播科",
    "url": "https:\/\/www.tainan.gov.tw\/News_Content.aspx?n=13370&s=8562270",
    "content": "發稿單位：社會局\n發稿時間：112年7月23日09:55\n\n南市社會局永康區社會福利服務中心於昨（22）日辦理「親子FUN電日-臺南貨櫃公園闖關趣」活動，邀請永康區弱勢家庭親子同樂，活動共有60位家長及小朋友參加，社會局結合在地知名的貨櫃公園動態場域，規劃親子闖關遊戲，讓家庭成員可以走出戶外、遠離3C產品，並促進親子互動凝聚家庭關係，共同創造親子正向的快樂記憶。\n\n黃偉哲市長表示，臺南市目前已成立安平、安南、北門、玉井、善化、麻豆、新豐、新營、永康、東區、南區、北區等12處社會福利服務中心，提供「以家庭為中心，社區為基礎」的福利服務，針對脆弱及弱勢家庭連結市府各項福利政策，舉凡經濟支持、婦幼照顧及弱勢關懷等支持服務。為增進弱勢家庭親子互動交流，暑假期間各區社會福利服務中心推出一系列的暑期活動，除減緩父母於兒少暑假期間的照顧壓力外，更讓兒少能夠接觸多樣態的正向活動，進而落實社會安全網，建構完整綿密家庭及社區支持網絡，共創幸福安全的社會環境。\n\n社會局局長盧禹璁指出為落實兒童權利公約提倡正當休閒權，運用暑假期間辦理多項親子同樂活動，期透過遊戲方式串起親子間情感，減少兒少不當使用3C產品沉迷網路或遭遇危險。社會局永康區社會福利服務中心規劃辦理「親子FUN暑假-同遊臺南貨櫃公園闖關趣」，使用臺南貨櫃公園場域，提供適切性親子活動，結合在地資源一同提供弱勢家庭休閒好去處，共創親子同樂好時光。\n\n社會局說明本次活動除搭配使用貨櫃公園動態遊具外，永康區社會福利服務中心更設計了「親子默契大考驗」、「親子時光留影」、「共築夢想天地」、「愛的直球對決」等4處親子闖關區。今年6歲的小遠來自單親家庭，在年邁阿公的陪同下興高采烈出席闖關活動，祖孫倆同心協力勇闖各關卡，在玩樂的同時，阿公也更了解小遠的想法增進彼此的親密關係，讓祖孫倆留下寶貴回憶。\n\n社會局提醒若民眾遇家中遭逢變故、或生活需要協助，都可就近至各社福中心諮詢求助、或電洽社會局詢問(電話：06-2993992)。",
    "tags": "#社會 #貨櫃公園"
}