{
    "published": "2022-04-28",
    "title": "回應時代力量有關騎樓整平暢通問題",
    "department": "臺南市政府工務局工程企劃科",
    "url": "https:\/\/www.tainan.gov.tw\/News_Content.aspx?n=13371&s=7889071",
    "content": "臺南市政府自100年起持續推動騎樓整平，至109年度已完成整平3,565公尺，順平410處，自101年起推動騎樓暢通計畫，透過舉辦友善騎樓競賽之方式由全民參予淨空騎樓，塑造友善通行騎樓之環境，臺南市累計迄今共暢通311條騎樓路段，累積長度139.7公里。\n其中時代力量提到民族路二段騎樓不平與雜物一事，工務局表示，該路段於100年即做過騎樓整平，103年又參加騎樓競賽淨空騎樓，而且每年辦理騎樓暢通計畫時，會再次複查已參與淨空騎樓的路段是否有維持暢通情形。若平時發現騎樓再遭店家佔用，由警方依法取締開罰。\n市長黃偉哲非常重視騎樓平順暢通的問題，僅管這項任務十分艱難，但工務局會努力持續推動騎樓整平暢通，讓民眾好行。\n另外，工務局說明，騎樓屬於私有產權，市政府辦理騎樓整平前先由當地里長、區公所里幹事與居民、店家溝通，於取得施工同意書之後，因施工過程需要打掉騎樓，取得住戶得土地使用同意書相當困難；市府除透過縮段施工期，並僅針對高低落差處施作無障礙斜坡道，無需整個整個區域騎樓打除施工﹅配合店家營業時間來調整施工期程，並採分段施作，避免全面施工，減短各店家影響時間，以提高屋主同意施作意願。\n 騎樓整平計劃目標致力打造身障者、老人、孕婦、幼兒等行動不便族群都方便的優質人行環境，將會持續努力推動，也期望能夠獲得民眾的支持，共同打造以人為本的友善又安全環境。\n\n發稿單位：養護工程科、使用管理科",
    "tags": "#回應時代力量有關騎樓整平暢通問題"
}