{
    "published": "2022-09-08",
    "title": "黃偉哲感謝青果西施號召社會大眾 贈柚傳愛助弱勢挺農民",
    "department": "新聞及國際關係處新聞傳播科",
    "url": "https:\/\/www.tainan.gov.tw\/News_Content.aspx?n=13370&s=7918800",
    "content": "發稿單位：新聞及國際關係處\n發稿日期：111年9月8日 9:41(更新11:02)\n發稿人：林靜怡\n\n中秋節是國人重要的民俗節日，也是麻豆柚農豐收採菓的季節，台南市長黃偉哲為感謝台南市百業國際安平學會創會理事長顏嘉縈響應照顧弱勢為優先之理念，連續兩年發起「文旦禮盒買一捐一」公益活動，南市府今(8)日舉辦捐贈儀式，由市長黃偉哲代表受贈並回贈感謝狀，感謝青果西施顏嘉縈女士，經營事業也不忘熱心公益，號召社會大眾共同捐贈文旦予南市弱勢家庭、身障小作所、新住民中心等社福單位。\n\n市長黃偉哲表示，感謝台南市百業國際安平學會，來協助社會上需要幫助的人，顏嘉縈女士的善行義舉令人讚許，顏理事長對社會弱勢的關懷化為實際行動，更對於推廣在地農產品也不遺餘力，由於疫情影響，經濟狀況受到衝擊的弱勢民眾增加，在政府資源有限的情況下，結合民間資源，期盼透過公私協力合作，邀請更多善心團體共襄盛舉，讓台南成為有愛的社會。\n\n顏嘉縈理事長傳承三代果菜批發事業，秉持用心經營回饋社會的理念，經常於工作之餘參加許多社團的公益活動，現在則擔任台南市百業國際安平學會創會理事長，帶領協會會員發起各項公益活動。\n\n顏嘉縈指出，此次捐贈是由她本人發起，300-D1國際獅子會台南市成功獅子會、300-D1國際獅子會台南市友聯獅子會、中華民國國民外交協會、台灣國際職業婦女協會、世界華人工商婦女企管協會、台南市餐旅教育協會、敏通新住民關懷協會、台南市企業友好交流協會、台南市美髮美容技術指導員職業工會、崑山科技大學校友總會、復興國中校友會、台南市家長協會、山甲青果行、青果西施青果社、富美紙器股份有限公司、德峰行糧食有限公司、甜蜜家飲餐飲集團、綠洲夢想咖啡，共同響應認購750箱文旦禮盒。\n\n社會局說明，750箱文旦禮盒將分別提供給大台南的兒少據點服務弱勢家庭、兒少安置機構、寄養家庭、日照佈建、身障社區居住、身障社區家托、身障社區精障會所、身障小作所、街友、新住民、脫貧家戶及私立仁愛之家育幼所的孩童，希望在中秋節這個重要節日，讓每一位收到禮盒的人，在享用台南麻豆在地果農採收的甜美文旦時都能感受到社會的愛心，度過一個溫暖有愛的中秋佳節。\n\n南市社會局為服務全市37區弱勢家庭及民眾，設有11處實物愛心銀行實體店面，倘若有經濟困難且有物資需求之市民，歡迎洽詢實物愛心銀行各分行。另外，為使有限的社福資源運用發揮更大效益，自108年起建置公益平台(https:\/\/ri.tainan.gov.tw\/)，提供相關弱勢家戶需求及各界物資捐贈，歡迎市民朋友上該平台加入會員，共同參與捐贈行列，如有相關問題請聯繫台南市政府社會局社會救助科06-2995686洽詢。",
    "tags": "#台南市百業國際安平學會愛心公益捐贈儀式"
}